CartoCosmos/CartoCosmos.py
CartoCosmos/__init__.py
CartoCosmos/geoServerLayers.json
CartoCosmos/planetary_gui.py
CartoCosmos/planetary_maps.py
CartoCosmos-1.0.5.data/data/geoServerLayers/geoServerLayers.json
test/__init__.py
test/planetary_gui_test.py
test/planetary_maps_test.py
CartoCosmos-1.0.5.dist-info/LICENSE
CartoCosmos-1.0.5.dist-info/METADATA
CartoCosmos-1.0.5.dist-info/WHEEL
CartoCosmos-1.0.5.dist-info/top_level.txt
CartoCosmos-1.0.5.dist-info/RECORD
