Metadata-Version: 2.1
Name: CartoCosmos
Version: 1.0.5
Summary: Virtual planetary mapping
Home-page: https://github.com/CartoCosmos/CartoCosmos
Author: CartoComos Development Team
Author-email: 
License: UNKNOWN
Platform: UNKNOWN
Classifier: Programming Language :: Python :: 3
Classifier: Operating System :: OS Independent
Requires-Python: >=3.6
Requires-Dist: ipyleaflet
Requires-Dist: ipywidgets
Requires-Dist: geojson
Requires-Dist: Shapely
